ExodusDecode.py
exodusdecode-1.1.dist-info/LICENSE
exodusdecode-1.1.dist-info/METADATA
exodusdecode-1.1.dist-info/WHEEL
exodusdecode-1.1.dist-info/RECORD
