Metadata-Version: 2.1
Name: ExodusDecode
Version: 1.1
Summary: Decode seed.seco file from Exodus)
License: MIT
Author: CodeLand
Requires-Python: >=3.7,<4.0
Classifier: License :: OSI Approved :: MIT License
Classifier: Programming Language :: Python :: 3
Classifier: Programming Language :: Python :: 3.7
Classifier: Programming Language :: Python :: 3.8
Classifier: Programming Language :: Python :: 3.9
Classifier: Programming Language :: Python :: 3.10
Classifier: Programming Language :: Python :: 3.11
Classifier: Programming Language :: Python :: 3.12
Requires-Dist: Cipherbcrypt (>=1.2,<2.0)
Requires-Dist: mnemonic (>=0.21,<0.22)
Requires-Dist: pycryptodome (>=3.20.0,<4.0.0)
